mysql_mcp_server/__init__.py
mysql_mcp_server/server.py
mysql_mcp_server1-0.1.0.dist-info/METADATA
mysql_mcp_server1-0.1.0.dist-info/WHEEL
mysql_mcp_server1-0.1.0.dist-info/entry_points.txt
mysql_mcp_server1-0.1.0.dist-info/licenses/LICENSE
mysql_mcp_server1-0.1.0.dist-info/RECORD
