Metadata-Version: 2.4
Name: mysql-mcp-server1
Version: 0.1.0
Summary: Add your description here
License-File: LICENSE
Requires-Python: >=3.11
Requires-Dist: mcp>=1.6.0
Requires-Dist: mysql-connector-python>=9.2.0
Requires-Dist: openai>=1.76.0
Requires-Dist: pip==25.0.1
